<?xml version="1.0" encoding="UTF-8" standalone="no"?>
<templates>

<template autoinsert="false" context="org.addondev.ui.template.Extension" deleted="false" 
	description="" enabled="true" id="org.addondev.ui.templates.project.firefox.installrdf" name="install.rdf">
&lt;?xml version="1.0" encoding="UTF-8"?&gt;
&lt;RDF xmlns="http://www.w3.org/1999/02/22-rdf-syntax-ns#" xmlns:em="http://www.mozilla.org/2004/em-rdf#"&gt;
  &lt;Description about="urn:mozilla:install-manifest"&gt;
    &lt;em:id&gt;${id}&lt;/em:id&gt;
    &lt;em:type&gt;2&lt;/em:type&gt;
    &lt;em:name&gt;${name}&lt;/em:name&gt;
    &lt;em:version&gt;${version}&lt;/em:version&gt;
    &lt;em:creator&gt;${creator}&lt;/em:creator&gt;
    &lt;em:optionsURL&gt;${options}&lt;/em:optionsURL&gt;
    &lt;em:targetApplication&gt;
      &lt;Description&gt;
        &lt;em:id&gt;${appid}&lt;/em:id&gt;
        &lt;em:minVersion&gt;${minversion}&lt;/em:minVersion&gt;
        &lt;em:maxVersion&gt;${maxversion}&lt;/em:maxVersion&gt;
      &lt;/Description&gt;
    &lt;/em:targetApplication&gt;
  &lt;/Description&gt;
&lt;/RDF&gt;
</template>

<template autoinsert="false" context="org.addondev.ui.template.Extension" deleted="false" 
	description="" enabled="true" id="org.addondev.ui.templates.project.firefox.chromemanifest" name="chrome.manifest">
content ${name} chrome/content/
skin    ${name} classic/1.0 chrome/skin/classic/
overlay chrome://browser/content/browser.xul chrome://${name}/content/overlay.xul
locale  ${name} ${locale} locale/${locale}/
</template>

<template autoinsert="false" context="org.addondev.ui.template.Extension" deleted="false" 
	description="" enabled="true" id="org.addondev.ui.templates.project.firefox.overlayxul" name="overlay.xul">
&lt;?xml version="1.0" encoding="UTF-8"?&gt;
&lt;?xml-stylesheet href="chrome://global/skin/global.css" type="text/css"?&gt;
&lt;?xml-stylesheet href="chrome://${name}/skin/overlay.css" type="text/css"?&gt;
&lt;!DOCTYPE overlay SYSTEM "chrome://${name}/locale/overlay.dtd"&gt;

&lt;overlay id="${name}-overlay" xmlns="http://www.mozilla.org/keymaster/gatekeeper/there.is.only.xul"&gt;
  &lt;script type="application/x-javascript;version=${javascriptvar}" src="chrome://${name}/content/overlay.js" /&gt;

  &lt;stringbundleset id="stringbundleset"&gt;
    &lt;stringbundle id="context-strings" src="chrome://${name}/locale/overlay.properties"/&gt;
  &lt;/stringbundleset&gt;

  ${context}
  ${menu}
  ${sidebar}
  ${toolbarbutton}
  ${toolbar}

&lt;/overlay&gt;
</template>

<template autoinsert="false" context="org.addondev.ui.template.Extension" deleted="false" 
	description="" enabled="true" id="org.addondev.ui.templates.project.firefox.menu" name="menu">
&lt;menupopup id="menu_ToolsPopup"&gt;
    &lt;menuitem id="${name}-menu" label="${name}.menu.label;"
              oncommand=""/&gt;
&lt;/menupopup&gt;
</template>

<template autoinsert="false" context="org.addondev.ui.template.Extension" deleted="false" 
	description="" enabled="true" id="org.addondev.ui.templates.project.firefox.context" name="context">
&lt;popup id="contentAreaContextMenu"&gt;
    &lt;menuitem id="${name}-context" label="&amp;${name}.context.label;"
              accesskey="${name}.context.accesskey;"
              insertafter="context-stop"
              oncommand=""/&gt;
&lt;/popup&gt;
</template>

<template autoinsert="false" context="org.addondev.ui.template.Extension" deleted="false" 
	description="" enabled="true" id="org.addondev.ui.templates.project.firefox.toolbarbutton" name="toolbarbutton">
&lt;toolbarpalette id="BrowserToolbarPalette"&gt;
  &lt;toolbarbutton id="toobarbutton-toolbar-button" class="toolbarbutton-1 chromeclass-toolbar-additional"
    label="&amp;${name}.toobarbutton.label;" tooltiptext="&amp;${name}.toobarbutton.tooltip;"
    oncommand="toobarbutton.onToolbarButtonCommand()"/&gt;
&lt;/toolbarpalette&gt;
</template>

<template autoinsert="false" context="org.addondev.ui.template.Extension" deleted="false" 
	description="" enabled="true" id="org.addondev.ui.templates.project.firefox.sidebar" name="sidebar">
&lt;menupopup id="viewSidebarMenu"&gt;
  &lt;menuitem key="key_openSidebar_all" observes="viewSidebar_all" /&gt;
&lt;/menupopup&gt;

&lt;keyset id="mainKeyset"&gt;
  &lt;key id="key_openSidebar_${name}" command="viewSidebar_${name}" /&gt;
&lt;/keyset&gt;

&lt;broadcasterset id="mainBroadcasterSet"&gt;
  &lt;broadcaster id="viewSidebar_${name}"
               label="&amp;${name}.sidebar.label;"
               autoCheck="false"
               type="checkbox"
               group="sidebar"
               sidebarurl="chrome://${name}/content/sidebar.xul"
               sidebartitle="&amp;${name}.sidebar.label;"
               oncommand="toggleSidebar('viewSidebar_${name}');" /&gt;
&lt;/broadcasterset&gt;	
</template>

<template autoinsert="false" context="org.addondev.ui.template.Extension" deleted="false" 
	description="" enabled="true" id="org.addondev.ui.templates.project.firefox.sidebarxul" name="sidebar.xul">
&lt;?xml version="1.0"?&gt;
&lt;?xml-stylesheet href="chrome://global/skin/" type"text/css" ?&gt;
&lt;!DOCTYPE page SYSTEM "chrome://${name}/locale/overlay.dtd"&gt;

&lt;page id="${name}Sidebar" title="&amp;${name}.sidebar.label;"
         xmlns="http://www.mozilla.org/keymaster/gatekeeper/there.is.only.xul"&gt;
  &lt;script src="sidebar.js"/&gt;

  &lt;vbox flex="1"&gt;
    &lt;label value="&amp;${name}.sidebar.label;" /&gt;
  &lt;/vbox&gt;
&lt;/page&gt;
</template>

<template autoinsert="false" context="org.addondev.ui.template.Extension" deleted="false" 
	description="" enabled="true" id="org.addondev.ui.templates.project.firefox.sidebarjs" name="sidebar.js">
function startup() {
                 
}

function shutdown() {

}

window.addEventListener("load", startup, false);
window.addEventListener("unload", shutdown, false);
</template>

<template autoinsert="false" context="org.addondev.ui.template.Extension" deleted="false" 
	description="" enabled="true" id="org.addondev.ui.templates.project.firefox.optionsxul" name="options.xul">
&lt;?xml version="1.0" encoding="UTF-8"?&gt;
&lt;?xml-stylesheet href="chrome://global/skin/" type="text/css"?&gt;
&lt;!DOCTYPE prefwindow SYSTEM "chrome://${name}/locale/options.dtd"&gt;
&lt;prefwindow id="${name}-preferences" xmlns="http://www.mozilla.org/keymaster/gatekeeper/there.is.only.xul" title="&amp;${name}.prefwindow.title;"&gt;
  &lt;prefpane id="pane1" label="&amp;${name}.pane1.title;"&gt;
    &lt;preferences&gt;
      &lt;preference id="boolpref1" name="extensions.${name}.boolpref" type="bool"/&gt;
      &lt;preference id="intpref1" name="extensions.${name}.intpref" type="int"/&gt;
      &lt;preference id="stringpref1" name="extensions.${name}.stringpref" type="string"/&gt;
    &lt;/preferences&gt;
    &lt;checkbox id="checkboolpref" preference="boolpref1" label="&amp;${name}.checkboolpref.label;" accesskey="&amp;${name}.checkboolpref.accesskey;"/&gt;
    &lt;label accesskey="&amp;${name}.intpref.accesskey;" control="textintpref"&gt;&amp;${name}.intpref.label;&lt;/label&gt;&lt;textbox id="textintpref" preference="intpref1"/&gt;
    &lt;label accesskey="&amp;${name}.stringpref.accesskey;" control="textstringpref"&gt;&amp;${name}.stringpref.label;&lt;/label&gt;&lt;textbox id="textstringpref" preference="stringpref1"/&gt;
  &lt;/prefpane&gt;
&lt;/prefwindow&gt;
</template>



<template autoinsert="false" context="org.addondev.ui.template.Extension" deleted="false" 
	description="" enabled="true" id="org.addondev.ui.templates.project.firefox.mainjs" name="overlay.js">

</template>

<template autoinsert="false" context="org.addondev.ui.template.Extension" deleted="false" 
	description="" enabled="true" id="org.addondev.ui.templates.project.firefox.prefsjs" name="prefs.js">

</template>

<template autoinsert="false" context="org.addondev.ui.template.Extension" deleted="false" 
	description="" enabled="true" id="org.addondev.ui.templates.project.firefox.overlaydtd" name="overlay.dtd">

</template>

<template autoinsert="false" context="org.addondev.ui.template.Extension" deleted="false" 
	description="" enabled="true" id="org.addondev.ui.templates.project.firefox.overlaycss" name="overlay.css">

</template>

</templates>